pyshrimp/__init__.py
pyshrimp/exception.py
pyshrimp/_internal/__init__.py
pyshrimp/_internal/locking/__init__.py
pyshrimp/_internal/locking/file_based_lock_internal.py
pyshrimp/_internal/locking/file_based_lock_posix.py
pyshrimp/_internal/locking/file_based_lock_windows.py
pyshrimp/_internal/pipes/__init__.py
pyshrimp/_internal/pipes/async_function.py
pyshrimp/_internal/pipes/utils.py
pyshrimp/_internal/scriptrunner/__init__.py
pyshrimp/_internal/scriptrunner/bootstrap.py
pyshrimp/_internal/scriptrunner/cli.py
pyshrimp/_internal/utils/__init__.py
pyshrimp/_internal/utils/errors.py
pyshrimp/_internal/utils/platformspecific.py
pyshrimp/_internal/utils/subprocess_utils.py
pyshrimp/_internal/wrapper/__init__.py
pyshrimp/_internal/wrapper/magicwrapper.py
pyshrimp/_internal/wrapper/magicwrapper_state.py
pyshrimp/_internal/wrapper/mainwrapper.py
pyshrimp/execution_pipeline/__init__.py
pyshrimp/execution_pipeline/pipeline.py
pyshrimp/execution_pipeline/pipeline_api.py
pyshrimp/execution_pipeline/pipeline_starter.py
pyshrimp/utils/__init__.py
pyshrimp/utils/collections.py
pyshrimp/utils/command.py
pyshrimp/utils/dotdict.py
pyshrimp/utils/filesystem.py
pyshrimp/utils/locking.py
pyshrimp/utils/logging.py
pyshrimp/utils/matching.py
pyshrimp/utils/parallel.py
pyshrimp/utils/splitter.py
pyshrimp/utils/string_wrapper.py
pyshrimp/utils/subprocess_utils.py
pyshrimp/utils/table_parser.py
pyshrimp/utils/wait.py
pyshrimp-0.8.0.dist-info/LICENSE.txt
pyshrimp-0.8.0.dist-info/METADATA
pyshrimp-0.8.0.dist-info/WHEEL
pyshrimp-0.8.0.dist-info/entry_points.txt
pyshrimp-0.8.0.dist-info/top_level.txt
pyshrimp-0.8.0.dist-info/RECORD
