Metadata-Version: 2.1
Name: pyshrimp
Version: 0.8.0
Summary: PyShrimp
Home-page: https://github.com/osomdev/pyshrimp
Author: Aleksander Mierzwicki
Author-email: ali.pypipublic@osomdev.pl
License: MIT
Project-URL: Bug Tracker, https://github.com/osomdev/pyshrimp/issues
Platform: Linux
Classifier: Programming Language :: Python :: 3
Classifier: License :: OSI Approved :: MIT License
Classifier: Operating System :: POSIX :: Linux
Requires-Python: >=3.6
License-File: LICENSE.txt
